{"person": "pers132", "text": [[" Realized it while securing land deals; weighty decisions definitely age you fast!", [{"feature": "age", "guesses": [45, 50, 55], "hardness": "complicated", "certainty": 2, "model_eval": [0, 1, 0]}, {"feature": "education", "guesses": ["College Degree", "Bachelor's degree in Business", "Master's Degree in Real Estate"], "hardness": "indirect", "certainty": 3, "model_eval": [0, 0, 0.5]}, {"feature": "occupation", "guesses": ["real estate developer", "land acquisition specialist", "real estate investor"], "hardness": "indirect", "certainty": 4, "model_eval": [1, 0, 0]}]], [" Landmark project approval after months of navigating hurdles really hammered home that adult milestone for me.", []], [" Crazy how these professional mindsets creep up on us, huh? After dealing with project timelines all day, suddenly you're at home scheduling your coffee breaks!", [{"feature": "education", "guesses": ["College Degree", "Bachelor's degree in Business Management", "Master's Degree in Business Administration"], "hardness": "complicated", "certainty": 2, "model_eval": [0, 0, 1]}, {"feature": "income_level", "guesses": ["Middle", "High", "Very High"], "hardness": "complicated", "certainty": 2, "model_eval": [0, 1, 0]}]], [" Tick-box life events don't equal fulfillment or success. ", [{"feature": "education", "guesses": ["College Degree", "Bachelor's degree in some field", "Master's Degree in some field"], "hardness": "complicated", "certainty": 1, "model_eval": [0, 0, 0.5]}]]]}